mercari/__init__.py
mercari/mercari.py
mercari-0.0.3.dist-info/METADATA
mercari-0.0.3.dist-info/WHEEL
mercari-0.0.3.dist-info/top_level.txt
mercari-0.0.3.dist-info/RECORD
