Metadata-Version: 2.1
Name: mercari
Version: 0.0.3
Summary: mercari api-like wrapper
Home-page: https://github.com/marvinody/mercari/
Author: marvinody
Author-email: manny@sadpanda.moe
License: UNKNOWN
Platform: UNKNOWN
Classifier: Programming Language :: Python :: 3.5
Requires-Dist: beautifulsoup4 (==4.8.1)
Requires-Dist: bleach (==3.1.0)
Requires-Dist: bs4 (==0.0.1)
Requires-Dist: certifi (==2019.11.28)
Requires-Dist: chardet (==3.0.4)
Requires-Dist: docutils (==0.15.2)
Requires-Dist: idna (==2.8)
Requires-Dist: pkginfo (==1.5.0.1)
Requires-Dist: Pygments (==2.5.2)
Requires-Dist: readme-renderer (==24.0)
Requires-Dist: requests (==2.22.0)
Requires-Dist: requests-toolbelt (==0.9.1)
Requires-Dist: six (==1.13.0)
Requires-Dist: soupsieve (==1.9.5)
Requires-Dist: tqdm (==4.40.1)
Requires-Dist: twine (==1.15.0)
Requires-Dist: urllib3 (==1.25.7)
Requires-Dist: webencodings (==0.5.1)
